gracie_dictionary_api/GracieAPIClassLoader.py
gracie_dictionary_api/GracieAuth.py
gracie_dictionary_api/GracieErrors.py
gracie_dictionary_api/__init__.py
gracie_dictionary_api/dictionary_controllers_classes/__init__.py
gracie_dictionary_api/dictionary_controllers_classes/abbreviationController.py
gracie_dictionary_api/dictionary_controllers_classes/autotuneIterationController.py
gracie_dictionary_api/dictionary_controllers_classes/autotuneRunController.py
gracie_dictionary_api/dictionary_controllers_classes/autotuneSkillController.py
gracie_dictionary_api/dictionary_controllers_classes/blacklistKeywordController.py
gracie_dictionary_api/dictionary_controllers_classes/briefController.py
gracie_dictionary_api/dictionary_controllers_classes/classStatusController.py
gracie_dictionary_api/dictionary_controllers_classes/classifierRiskRuleController.py
gracie_dictionary_api/dictionary_controllers_classes/clusterController.py
gracie_dictionary_api/dictionary_controllers_classes/clusterGroupController.py
gracie_dictionary_api/dictionary_controllers_classes/clusterSetController.py
gracie_dictionary_api/dictionary_controllers_classes/compoundLexemeController.py
gracie_dictionary_api/dictionary_controllers_classes/continentController.py
gracie_dictionary_api/dictionary_controllers_classes/countryController.py
gracie_dictionary_api/dictionary_controllers_classes/databasesController.py
gracie_dictionary_api/dictionary_controllers_classes/documentController.py
gracie_dictionary_api/dictionary_controllers_classes/downloadController.py
gracie_dictionary_api/dictionary_controllers_classes/enginesClusterController.py
gracie_dictionary_api/dictionary_controllers_classes/entityRiskRuleController.py
gracie_dictionary_api/dictionary_controllers_classes/featureClassController.py
gracie_dictionary_api/dictionary_controllers_classes/featureCodeController.py
gracie_dictionary_api/dictionary_controllers_classes/geoCodesController.py
gracie_dictionary_api-100.6.0.28.1704924468.dist-info/LICENSE.txt
gracie_dictionary_api-100.6.0.28.1704924468.dist-info/METADATA
gracie_dictionary_api-100.6.0.28.1704924468.dist-info/WHEEL
gracie_dictionary_api-100.6.0.28.1704924468.dist-info/top_level.txt
gracie_dictionary_api-100.6.0.28.1704924468.dist-info/zip-safe
gracie_dictionary_api-100.6.0.28.1704924468.dist-info/RECORD
